{
  "name": "blockquote",
  "type": "component",
  "description": "Styled quote blocks with optional citation",
  "dependencies": [],
  "registryDependencies": [],
  "files": [
    {
      "path": "blockquote.tsx",
      "content": "import * as React from \"react\"\nimport { cn } from \"@/lib/utils\"\n\nexport interface BlockquoteProps extends React.HTMLAttributes<HTMLQuoteElement> {\n  cite?: string\n}\n\nexport const Blockquote = React.forwardRef<HTMLQuoteElement, BlockquoteProps>(\n  ({ children, className, cite, ...props }, ref) => (\n    <blockquote\n      ref={ref}\n      className={cn(\n        \"border-l-4 border-primary pl-4 py-2 my-4 italic text-foreground bg-primary/5\",\n        className\n      )}\n      {...props}\n    >\n      {children}\n      {cite && (\n        <footer className=\"text-sm text-muted-foreground mt-2 not-italic\">\n          — {cite}\n        </footer>\n      )}\n    </blockquote>\n  )\n)\nBlockquote.displayName = \"Blockquote\"\n",
      "integrity": "sha256-oKaTyf852KqrEZQsjFKb9M3ETTjmp8MF2JP5D92PzL8="
    }
  ]
}
